{
  "id": "q_12",
  "band": 8,
  "content": "To be perfectly honest, while I have always been a **keen admirer** of the arts, I don’t think I have the temperament or the raw talent to pursue it as a full-time profession. Being an artist requires a level of unwavering dedication and a willingness to embrace financial instability that I personally find quite daunting. However, I do view creative expression as a vital **creative outlet** to relieve stress and **recharge my batteries** after a long week of work.\n\nThat being said, if I were to explore this path, I would likely gravitate toward digital illustration or graphic design. It is a **pivotal field** in the modern era, and I am fascinated by the **interplay between** technology and traditional aesthetics. Engaging with such a medium would allow me to **expand my horizons** and develop a more **nuanced understanding** of visual storytelling, even if it remains a passionate hobby rather than a primary career.\n\nUltimately, I prefer to keep my artistic pursuits as a **tranquil sanctuary** away from the **hustle and bustle** of professional life. I believe that once a passion becomes a primary source of income, it can sometimes lose its spark due to commercial pressure. By remaining an enthusiast rather than a professional, I can continue to appreciate the **foundational pillars** of art without the burden of meeting strict deadlines or critical expectations.",
  "timestamp": "2026-04-29T01:40:15.143854",
  "source": "Phạm Tiến Dũng Gia Sư"
}