{
  "id": "q_22",
  "band": 8,
  "content": "To be perfectly honest, I tend to be quite **cautious** when it comes to handling **cumbersome** objects, as I’m acutely aware of the potential for physical strain or injury. If I find myself needing to transport a particularly heavy item, my first **port of call** is usually to seek assistance. Whether it’s a friend, a family member, or a professional mover, I believe that **many hands make light work**, and it’s always better to prioritize safety over personal pride.\n\nIn situations where I have to manage on my own, I rely heavily on **mechanical aids** to mitigate the physical burden. For instance, if I’m moving furniture or heavy groceries, I’ll invariably use a trolley or a sturdy suitcase with multi-directional wheels. This allows me to **leverage** the equipment rather than relying solely on my own strength. I’ve found that using the right tools can transform a **grueling** task into a much more manageable endeavor, preventing unnecessary **wear and tear** on my body.\n\nFurthermore, I am quite **mindful** of proper lifting techniques if I absolutely must lift something manually. I make a point of bending at the knees and keeping my back straight to avoid any **acute** lower back pain. Ultimately, I try to work smarter, not harder, by planning the route beforehand to ensure there are no obstacles in my path. Being **methodical** in these situations is **paramount** to ensuring that the task is completed efficiently without any **mishaps**.",
  "timestamp": "2026-04-29T00:38:26.666806",
  "source": "Phạm Tiến Dũng Gia Sư"
}