{
  "id": "Q2_P1_Mirrors_1_idiom",
  "vocab": [
    {
      "word": "a feast for the eyes",
      "ipa": "/ə fiːst fə ði aɪz/",
      "meaning": "một cảnh tượng mãn nhãn/đẹp mắt",
      "example": "I wouldn't say my reflection is a feast for the eyes, but I do check the mirror to ensure my outfit is coordinated.",
      "type": "idiom"
    },
    {
      "word": "vanity is my middle name",
      "ipa": "/ˈvænəti ɪz maɪ ˈmɪdl neɪm/",
      "meaning": "là người rất chú trọng vẻ bề ngoài (nói vui)",
      "example": "Admittedly, vanity is my middle name, so I probably glance at my reflection more often than the average person.",
      "type": "idiom"
    },
    {
      "word": "look like a sight for sore eyes",
      "ipa": "/lʊk laɪk ə saɪt fə sɔːr aɪz/",
      "meaning": "trông rất dễ chịu/vui mừng khi thấy (thường dùng sau khi vừa tút tát lại)",
      "example": "After a long day at the office, seeing myself finally cleaned up in the mirror makes me feel like a sight for sore eyes.",
      "type": "idiom"
    },
    {
      "word": "warts and all",
      "ipa": "/wɔːts ənd ɔːl/",
      "meaning": "chấp nhận mọi khuyết điểm/toàn bộ sự thật",
      "example": "As I’ve grown older, I’ve learned to appreciate what I see in the mirror, warts and all, without being too critical.",
      "type": "idiom"
    },
    {
      "word": "cut a long story short",
      "ipa": "/kʌt ə lɒŋ ˈstɔːri ʃɔːt/",
      "meaning": "tóm lại là (dùng để chuyển ý khi kể về thói quen soi gương)",
      "example": "I used to be obsessed with my hair but, to cut a long story short, I now only look in the mirror twice a day.",
      "type": "idiom"
    },
    {
      "word": "spick and span",
      "ipa": "/spɪk ənd spæn/",
      "meaning": "gọn gàng, sạch sẽ, ngăn nắp",
      "example": "I mainly use the mirror to ensure that my grooming is spick and span before I head out for a formal event.",
      "type": "idiom"
    },
    {
      "word": "give someone a run for their money",
      "ipa": "/ɡɪv ˈsʌmwʌn ə rʌn fə ðeə ˈmʌni/",
      "meaning": "tốt/đẹp không kém gì ai đó (thường nói đùa về sự tự tin)",
      "example": "When I'm fully dressed up, I like to think my reflection could give a movie star a run for their money.",
      "type": "idiom"
    },
    {
      "word": "at the drop of a hat",
      "ipa": "/æt ðə drɒp əv ə hæt/",
      "meaning": "ngay lập tức/bất cứ khi nào có cơ hội",
      "example": "My younger sister is quite vain; she'll stop to check herself in any reflective surface at the drop of a hat.",
      "type": "idiom"
    },
    {
      "word": "the apple of one's eye",
      "ipa": "/ði ˈæpl əv wʌnz aɪ/",
      "meaning": "người/vật được yêu quý nhất (dùng khi nói về việc tự yêu bản thân)",
      "example": "I don't look in the mirror because I think I'm the apple of my own eye; it’s purely out of a need for basic tidiness.",
      "type": "idiom"
    },
    {
      "word": "in the flesh",
      "ipa": "/ɪn ðə fleʃ/",
      "meaning": "bằng xương bằng thịt/ngoài đời thực",
      "example": "Sometimes I’m surprised by how different I look in the mirror compared to photos—it’s the only way to see myself in the flesh, so to speak.",
      "type": "idiom"
    }
  ],
  "type": "idiom"
}