{
  "id": "Q2_P1_Views_4",
  "vocab": [
    {
      "word": "visual crescendo",
      "ipa": "/ˈvɪʒuəl krəˈʃendəʊ/",
      "meaning": "đỉnh điểm của vẻ đẹp thị giác (sự choáng ngợp tăng dần)",
      "example": "Reaching the summit felt like a visual crescendo, where every element of the valley below aligned perfectly.",
      "type": "vocabulary"
    },
    {
      "word": "monochromatic majesty",
      "ipa": "/ˌmɒnəkrəˈmætɪk ˈmædʒəsti/",
      "meaning": "vẻ uy nghiêm đơn sắc (thường dùng cho cảnh tuyết hoặc sa mạc)",
      "example": "The endless salt flats offered a sense of monochromatic majesty that made me feel like I was on another planet.",
      "type": "vocabulary"
    },
    {
      "word": "a subterranean marvel",
      "ipa": "/ə ˌsʌbtəˈreɪniən ˈmɑːrvl/",
      "meaning": "một kỳ quan dưới lòng đất",
      "example": "The illuminated stalactites inside the cave were a subterranean marvel that I'll never forget.",
      "type": "vocabulary"
    },
    {
      "word": "topographical drama",
      "ipa": "/ˌtɒpəˈɡræfɪkl ˈdrɑːmə/",
      "meaning": "sự kỳ vĩ/kịch tính của địa hình",
      "example": "I was captivated by the topographical drama of the sheer cliffs plunging straight into the turbulent ocean.",
      "type": "vocabulary"
    },
    {
      "word": "verdant amphitheater",
      "ipa": "/ˈvɜːrdnt ˈæmfɪθiətər/",
      "meaning": "một lòng chảo xanh mướt (như rạp hát ngoài trời)",
      "example": "We stumbled upon a hidden valley that looked like a giant verdant amphitheater tucked away from the world.",
      "type": "vocabulary"
    },
    {
      "word": "an ephemeral brilliance",
      "ipa": "/ən ɪˈfemərəl ˈbrɪliəns/",
      "meaning": "vẻ rực rỡ phù du (thoáng qua nhanh chóng)",
      "example": "The double rainbow lasted only minutes, but its ephemeral brilliance left a lasting mark on my heart.",
      "type": "vocabulary"
    },
    {
      "word": "atmospheric perspective",
      "ipa": "/ˌætməsˈfɪrɪk pərˈspektɪv/",
      "meaning": "phối cảnh không trung (cảnh vật mờ dần theo khoảng cách)",
      "example": "The layers of blue mountains receding into the mist created a stunning atmospheric perspective.",
      "type": "vocabulary"
    },
    {
      "word": "unencumbered by civilization",
      "ipa": "/ˌʌnɪnˈkʌmbərd baɪ ˌsɪvələˈzeɪʃn/",
      "meaning": "không bị vướng bận/ảnh hưởng bởi văn minh",
      "example": "Looking out at the vast tundra, unencumbered by civilization, I felt a rare sense of absolute freedom.",
      "type": "vocabulary"
    },
    {
      "word": "a chromatic explosion",
      "ipa": "/ə krəˈmætɪk ɪkˈspləʊʒn/",
      "meaning": "một sự bùng nổ của màu sắc",
      "example": "The flower fields in spring were a chromatic explosion that no photograph could ever truly capture.",
      "type": "vocabulary"
    },
    {
      "word": "ethereal luminescence",
      "ipa": "/ɪˈθɪəriəl ˌluːmɪˈnesns/",
      "meaning": "sự phát sáng huyền ảo (như lân quang hoặc ánh trăng)",
      "example": "The sea was filled with bioluminescent plankton, creating an ethereal luminescence that mirrored the stars above.",
      "type": "vocabulary"
    }
  ],
  "type": "vocabulary"
}