{
  "id": "Q2_P1_Reading_4",
  "vocab": [
    {
      "word": "meticulous perusal",
      "ipa": "/məˈtɪkjələs pəˈruːzl/",
      "meaning": "sự đọc kỹ lưỡng, cẩn thận",
      "example": "For academic papers, I opt for meticulous perusal to ensure I don't overlook any critical data.",
      "type": "vocabulary"
    },
    {
      "word": "glance through",
      "ipa": "/ɡlɑːns θruː/",
      "meaning": "đọc lướt qua nhanh",
      "example": "If I'm just checking the morning news, I usually glance through the headlines to get the gist.",
      "type": "vocabulary"
    },
    {
      "word": "extract key information",
      "ipa": "/ɪkˈstrækt kiː ˌɪnfəˈmeɪʃn/",
      "meaning": "trích xuất thông tin chủ chốt",
      "example": "Scanning is my preferred method when I need to extract key information from a dense report in a hurry.",
      "type": "vocabulary"
    },
    {
      "word": "lose oneself in",
      "ipa": "/luːz wʌnˈself ɪn/",
      "meaning": "đắm chìm vào (một cuốn sách/văn bản)",
      "example": "I love to lose myself in a gripping novel, which naturally requires a more detailed reading approach.",
      "type": "vocabulary"
    },
    {
      "word": "superficial understanding",
      "ipa": "/ˌsuːpəˈfɪʃl ˌʌndəˈstændɪŋ/",
      "meaning": "sự hiểu biết hời hợt/trên bề mặt",
      "example": "Scanning often only provides a superficial understanding, which isn't enough for complex technical manuals.",
      "type": "vocabulary"
    },
    {
      "word": "scrutinize the text",
      "ipa": "/ˈskruːtənaɪz ðə tekst/",
      "meaning": "xem xét/đọc văn bản một cách cực kỳ chi tiết",
      "example": "When reviewing a contract, it is vital to scrutinize the text to avoid any legal pitfalls.",
      "type": "vocabulary"
    },
    {
      "word": "selective reading",
      "ipa": "/sɪˈlektɪv ˈriːdɪŋ/",
      "meaning": "đọc có chọn lọc",
      "example": "I practice selective reading when I’m researching, focusing only on the chapters relevant to my thesis.",
      "type": "vocabulary"
    },
    {
      "word": "cognitive load",
      "ipa": "/ˈkɒɡnətɪv ləʊd/",
      "meaning": "áp lực/tải trọng nhận thức",
      "example": "Detailed reading demands a higher cognitive load, so I save it for when I'm most alert.",
      "type": "vocabulary"
    },
    {
      "word": "dig deeper into",
      "ipa": "/dɪɡ ˈdiːpə(r) ˈɪntə/",
      "meaning": "tìm hiểu sâu hơn về cái gì",
      "example": "If a headline catches my eye, I will then dig deeper into the article to understand the underlying causes.",
      "type": "vocabulary"
    },
    {
      "word": "time-efficient",
      "ipa": "/ˈtaɪm ɪˈfɪʃnt/",
      "meaning": "tiết kiệm/hiệu quả về mặt thời gian",
      "example": "Scanning is a time-efficient strategy for professionals who have to deal with hundreds of emails daily.",
      "type": "vocabulary"
    }
  ],
  "type": "vocabulary"
}