{
  "id": "Q2_P1_Mirrors_1_coll",
  "vocab": [
    {
      "word": "cursory inspection",
      "ipa": "/ˈkɜːrsəri ɪnˈspekʃn/",
      "meaning": "sự kiểm tra chớp nhoáng/sơ sài",
      "example": "I usually give myself a cursory inspection in the mirror before leaving for work just to ensure my collar isn't tucked in.",
      "type": "collocation"
    },
    {
      "word": "fixate on perceived flaws",
      "ipa": "/ˈfɪkseɪt ɒn pəˈsiːvd flɔːz/",
      "meaning": "ám ảnh/chăm chú vào những khuyết điểm tự cảm thấy",
      "example": "I try not to spend too much time looking at my reflection because I tend to fixate on perceived flaws that others wouldn't even notice.",
      "type": "collocation"
    },
    {
      "word": "project an air of confidence",
      "ipa": "/prəˈdʒekt ən eər əv ˈkɒnfɪdəns/",
      "meaning": "tỏa ra vẻ tự tin",
      "example": "Practicing my speech in front of a mirror helps me project an air of confidence before a major presentation.",
      "type": "collocation"
    },
    {
      "word": "reassure oneself of one's appearance",
      "ipa": "/ˌriːəˈʃʊə wʌnˈself əv wʌnz əˈpɪərəns/",
      "meaning": "tự trấn an về diện mạo của mình",
      "example": "I find myself glancing at shop windows occasionally just to reassure myself of my appearance after a long commute.",
      "type": "collocation"
    },
    {
      "word": "adjust one’s attire",
      "ipa": "/əˈdʒʌst wʌnz əˈtaɪə/",
      "meaning": "chỉnh sửa trang phục",
      "example": "A mirror is essential for me to adjust my attire and make sure my tie is perfectly straight.",
      "type": "collocation"
    },
    {
      "word": "preen in front of the glass",
      "ipa": "/priːn ɪn frʌnt əv ðə ɡlɑːs/",
      "meaning": "tỉa tót/chăm chút diện mạo trước gương",
      "example": "I wouldn't say I'm vain, but I do spend a few minutes each morning to preen in front of the glass.",
      "type": "collocation"
    },
    {
      "word": "distorted self-image",
      "ipa": "/dɪˈstɔːrtɪd self ˈɪmɪdʒ/",
      "meaning": "hình ảnh bản thân bị bóp méo/sai lệch",
      "example": "Spending excessive time analyzing one's reflection can sometimes lead to a distorted self-image.",
      "type": "collocation"
    },
    {
      "word": "maintain a polished image",
      "ipa": "/meɪnˈteɪn ə ˈpɒlɪʃt ˈɪmɪdʒ/",
      "meaning": "duy trì một hình ảnh bóng bẩy/chỉn chu",
      "example": "As a public speaker, looking in the mirror frequently is a necessity to maintain a polished image throughout the day.",
      "type": "collocation"
    },
    {
      "word": "briefly check one's reflection",
      "ipa": "/ˈbriːfli tʃek wʌnz rɪˈflekʃn/",
      "meaning": "kiểm tra nhanh hình ảnh phản chiếu của mình",
      "example": "Whenever I pass a mirror in a hallway, I might briefly check my reflection out of habit.",
      "type": "collocation"
    },
    {
      "word": "self-reflective moment",
      "ipa": "/self rɪˈflektɪv ˈməʊmənt/",
      "meaning": "khoảnh khắc tự suy ngẫm (cả nghĩa đen và nghĩa bóng)",
      "example": "To me, the mirror provides a self-reflective moment where I can gather my thoughts while brushing my teeth.",
      "type": "collocation"
    }
  ],
  "type": "collocation"
}