{
  "id": "Q2_P1_Reading_1_coll",
  "vocab": [
    {
      "word": "a page-turner",
      "ipa": "/ə peɪdʒ ˈtɜːnə(r)/",
      "meaning": "một cuốn sách cực kỳ lôi cuốn (khiến người đọc lật trang liên tục)",
      "example": "I particularly enjoy thrillers because they are usually real page-turners that keep me on the edge of my seat.",
      "type": "collocation"
    },
    {
      "word": "immerse oneself in",
      "ipa": "/ɪˈmɜːs wʌnˈself ɪn/",
      "meaning": "đắm mình vào cái gì đó",
      "example": "There's nothing more relaxing than immersing oneself in a high-fantasy world after a taxing day at work.",
      "type": "collocation"
    },
    {
      "word": "compelling narrative",
      "ipa": "/kəmˈpelɪŋ ˈnærətɪv/",
      "meaning": "lối dẫn chuyện đầy thuyết phục/hấp dẫn",
      "example": "I’m often drawn to historical fiction that features a compelling narrative and well-developed characters.",
      "type": "collocation"
    },
    {
      "word": "cultivate a habit",
      "ipa": "/ˈkʌltɪveɪt ə ˈhæbɪt/",
      "meaning": "nuôi dưỡng/trau dồi một thói quen",
      "example": "I have been trying to cultivate the habit of reading for at least thirty minutes before going to bed.",
      "type": "collocation"
    },
    {
      "word": "broaden one's perspective",
      "ipa": "/ˈbrɔːdn wʌnz pəˈspektɪv/",
      "meaning": "mở rộng quan điểm/góc nhìn của ai đó",
      "example": "Reading international literature is a fantastic way to broaden your perspective on global social issues.",
      "type": "collocation"
    },
    {
      "word": "a wealth of knowledge",
      "ipa": "/ə welθ əv ˈnɒlɪdʒ/",
      "meaning": "một kho tàng tri thức",
      "example": "Non-fiction books provide a wealth of knowledge that can be directly applied to my professional life.",
      "type": "collocation"
    },
    {
      "word": "evocative language",
      "ipa": "/ɪˈvɒkətɪv ˈlæŋɡwɪdʒ/",
      "meaning": "ngôn từ gợi hình/gợi cảm",
      "example": "The author uses such evocative language that I can almost smell the sea air described in the chapters.",
      "type": "collocation"
    },
    {
      "word": "formative years",
      "ipa": "/ˈfɔːmətɪv jɪəz/",
      "meaning": "những năm tháng hình thành nhân cách (tuổi thơ)",
      "example": "Reading adventure stories during my formative years really sparked my curiosity about the world.",
      "type": "collocation"
    },
    {
      "word": "digital distractions",
      "ipa": "/ˈdɪdʒɪtl dɪˈstrækʃnz/",
      "meaning": "những sự xao nhãng từ thiết bị điện tử",
      "example": "I prefer physical books because they allow me to escape from constant digital distractions like social media notifications.",
      "type": "collocation"
    },
    {
      "word": "prolific writer",
      "ipa": "/prəˈlɪfɪk ˈraɪtə(r)/",
      "meaning": "nhà văn có sức sáng tác dồi dào (viết rất nhiều tác phẩm)",
      "example": "I'm a huge fan of Stephen King; he is such a prolific writer that I always have something new to read.",
      "type": "collocation"
    }
  ],
  "type": "collocation"
}