{
  "id": "Q2_P1_Mirrors_2_coll",
  "vocab": [
    {
      "word": "a focal point",
      "ipa": "/ə ˈfəʊkl pɔɪnt/",
      "meaning": "điểm nhấn trung tâm",
      "example": "I purchased a large, sunburst-style mirror to act as a focal point in my otherwise minimalist living room.",
      "type": "collocation"
    },
    {
      "word": "enhance the ambiance",
      "ipa": "/ɪnˈhɑːns ðə ˈæmbiəns/",
      "meaning": "cải thiện/làm đẹp bầu không khí",
      "example": "We decided to buy a series of small decorative mirrors to enhance the ambiance and reflect the candlelight during dinner parties.",
      "type": "collocation"
    },
    {
      "word": "etched glass patterns",
      "ipa": "/etʃt ɡlɑːs ˈpætnz/",
      "meaning": "họa tiết khắc trên kính",
      "example": "I was captivated by a vintage mirror featuring intricate etched glass patterns along its border.",
      "type": "collocation"
    },
    {
      "word": "tarnish-resistant coating",
      "ipa": "/ˈtɑːrnɪʃ rɪˈzɪstənt ˈkəʊtɪŋ/",
      "meaning": "lớp phủ chống xỉn màu/ố mờ",
      "example": "When shopping for a bathroom mirror, I specifically looked for one with a tarnish-resistant coating to withstand the humidity.",
      "type": "collocation"
    },
    {
      "word": "wall-mounted fixture",
      "ipa": "/wɔːl ˈmaʊntɪd ˈfɪkstʃər/",
      "meaning": "vật cố định treo tường",
      "example": "Instead of a standing one, I opted for a sleek wall-mounted fixture to save floor space in my dressing area.",
      "type": "collocation"
    },
    {
      "word": "reflect the surrounding landscape",
      "ipa": "/rɪˈflekt ðə səˈraʊndɪŋ ˈlændskeɪp/",
      "meaning": "phản chiếu phong cảnh xung quanh",
      "example": "We placed a massive mirror in the sunroom to reflect the surrounding landscape, effectively bringing the outdoors in.",
      "type": "collocation"
    },
    {
      "word": "high-definition clarity",
      "ipa": "/haɪ ˌdefɪˈnɪʃn ˈklærəti/",
      "meaning": "độ rõ nét cao (hình ảnh chân thực)",
      "example": "I invested in a professional makeup mirror because it offers high-definition clarity without any distortion.",
      "type": "collocation"
    },
    {
      "word": "geometric configuration",
      "ipa": "/ˌdʒiːəˈmetrɪk kənˌfɪɡjuˈreɪʃn/",
      "meaning": "cấu trúc/bố cục hình khối",
      "example": "I recently acquired a mirror with a unique geometric configuration that adds a modern touch to my bedroom.",
      "type": "collocation"
    },
    {
      "word": "reclaim from an estate sale",
      "ipa": "/rɪˈkleɪm frəm ən ɪˈsteɪt seɪl/",
      "meaning": "mua lại/tìm lại được từ một buổi thanh lý tài sản",
      "example": "My favorite piece is a heavy oak mirror that I managed to reclaim from an estate sale in the countryside.",
      "type": "collocation"
    },
    {
      "word": "minimalist wooden trim",
      "ipa": "/ˈmɪnɪməlɪst ˈwʊdn trɪm/",
      "meaning": "viền gỗ tối giản",
      "example": "I'm looking for a mirror with a minimalist wooden trim to match the Scandinavian vibe of my home.",
      "type": "collocation"
    }
  ],
  "type": "collocation"
}