{
  "id": "q_17",
  "vocab": [
    {
      "word": "unconventional medium",
      "ipa": "/ˌʌn.kənˈven.ʃən.əl ˈmiː.di.əm/",
      "meaning": "chất liệu nghệ thuật độc lạ (không truyền thống)",
      "example": "The exhibition featured artists working with unconventional media like recycled plastic and digital light.",
      "type": "vocabulary"
    },
    {
      "word": "provoke thought",
      "ipa": "/prəˈvəʊk θɔːt/",
      "meaning": "kích thích suy nghĩ, gợi mở tư duy",
      "example": "I appreciate contemporary art because it aims to provoke thought rather than just being decorative.",
      "type": "vocabulary"
    },
    {
      "word": "exquisite brushwork",
      "ipa": "/ɪkˈskwɪz.ɪt ˈbrʌʃ.wɜːk/",
      "meaning": "kỹ thuật vẽ/nét bút tinh xảo",
      "example": "I stood in front of the oil painting for ages, admiring the exquisite brushwork and the depth of color.",
      "type": "vocabulary"
    },
    {
      "word": "avant-garde",
      "ipa": "/ˌæv.ɒ̃ˈɡɑːd/",
      "meaning": "mang tính tiên phong, mới lạ và phá cách",
      "example": "The gallery is famous for showcasing avant-garde installations that challenge our traditional notions of art.",
      "type": "vocabulary"
    },
    {
      "word": "a feast for the eyes",
      "ipa": "/ə fiːst fɔːr ði aɪz/",
      "meaning": "một bữa tiệc thị giác (thứ gì đó rất đẹp để ngắm nhìn)",
      "example": "The retrospective of Van Gogh’s work was a true feast for the eyes, bursting with vibrant yellows and blues.",
      "type": "vocabulary"
    },
    {
      "word": "monochromatic",
      "ipa": "/ˌmɒn.ə.krəˈmæt.ɪk/",
      "meaning": "đơn sắc (chỉ sử dụng một màu hoặc các sắc độ của một màu)",
      "example": "One particular room was dedicated to monochromatic sketches, which felt incredibly raw and powerful.",
      "type": "vocabulary"
    },
    {
      "word": "art aficionado",
      "ipa": "/ɑːt əˌfɪʃ.i.əˈnɑː.dəʊ/",
      "meaning": "người cực kỳ am hiểu và đam mê nghệ thuật",
      "example": "While I’m not exactly an art aficionado, I find wandering through galleries to be a very therapeutic experience.",
      "type": "vocabulary"
    },
    {
      "word": "subconscious mind",
      "ipa": "/ˌsʌbˈkɒn.ʃəs maɪnd/",
      "meaning": "tâm trí tiềm thức",
      "example": "Surrealist paintings often try to tap into the subconscious mind, creating dream-like and bizarre imagery.",
      "type": "vocabulary"
    },
    {
      "word": "stark contrast",
      "ipa": "/stɑːk ˈkɒn.trɑːst/",
      "meaning": "sự tương phản hoàn toàn/gay gắt",
      "example": "The use of shadows in the gallery created a stark contrast with the brightly lit marble sculptures.",
      "type": "vocabulary"
    },
    {
      "word": "timeless masterpiece",
      "ipa": "/ˈtaɪm.ləs ˈmɑː.stə.piːs/",
      "meaning": "kiệt tác vượt thời gian",
      "example": "Seeing a timeless masterpiece in person is a far more moving experience than viewing it on a screen.",
      "type": "vocabulary"
    }
  ],
  "type": "vocabulary"
}