{
  "id": "q_22",
  "vocab": [
    {
      "word": "sedentary lifestyle",
      "ipa": "/ˈsedntri ˈlaɪfstaɪl/",
      "meaning": "lối sống ít vận động (dùng để nêu lý do tập thể thao)",
      "example": "I took up swimming primarily to counteract the effects of a sedentary lifestyle spent behind a desk.",
      "type": "vocabulary"
    },
    {
      "word": "peak physical condition",
      "ipa": "/piːk ˈfɪzɪkl kənˈdɪʃn/",
      "meaning": "trạng thái thể chất đỉnh cao",
      "example": "Professional athletes spend years of disciplined training to remain in peak physical condition.",
      "type": "vocabulary"
    },
    {
      "word": "a sense of accomplishment",
      "ipa": "/ə sens əv əˈkʌmplɪʃmənt/",
      "meaning": "cảm giác đạt được thành tựu",
      "example": "Completing a marathon gives you an unparalleled sense of accomplishment that boosts your self-esteem.",
      "type": "vocabulary"
    },
    {
      "word": "strenuous exercise",
      "ipa": "/ˈstrenjuəs ˈeksəsaɪz/",
      "meaning": "bài tập cường độ cao, vất vả",
      "example": "I prefer moderate activities like jogging over more strenuous exercise like weightlifting.",
      "type": "vocabulary"
    },
    {
      "word": "team spirit",
      "ipa": "/tiːm ˈspɪrɪt/",
      "meaning": "tinh thần đồng đội",
      "example": "Basketball is a great way to foster team spirit and learn how to cooperate effectively with others.",
      "type": "vocabulary"
    },
    {
      "word": "hike in the great outdoors",
      "ipa": "/haɪk ɪn ðə ɡreɪt ˌaʊtˈdɔːz/",
      "meaning": "đi bộ đường dài giữa thiên nhiên hùng vĩ",
      "example": "For me, nothing beats a long hike in the great outdoors to reconnect with nature and clear my mind.",
      "type": "vocabulary"
    },
    {
      "word": "competitive streak",
      "ipa": "/kəmˈpetətɪv striːk/",
      "meaning": "tính cách ham mê cạnh tranh, đua tranh",
      "example": "My competitive streak always comes out when I'm playing tennis with my older brother.",
      "type": "vocabulary"
    },
    {
      "word": "core strength",
      "ipa": "/kɔː(r) streŋθ/",
      "meaning": "sức mạnh cơ lõi (bụng, lưng, hông)",
      "example": "Pilates is specifically designed to improve your core strength and overall body posture.",
      "type": "vocabulary"
    },
    {
      "word": "release endorphins",
      "ipa": "/rɪˈliːs ɪnˈdɔːfɪnz/",
      "meaning": "giải phóng endorphin (hormone hạnh phúc)",
      "example": "Any form of vigorous sport helps to release endorphins, which act as a natural stress reliever.",
      "type": "vocabulary"
    },
    {
      "word": "hand-eye coordination",
      "ipa": "/hænd aɪ kəʊˌɔːdɪˈneɪʃn/",
      "meaning": "khả năng phối hợp tay và mắt",
      "example": "Sports like table tennis are excellent for honing your hand-eye coordination and reflexes.",
      "type": "vocabulary"
    }
  ],
  "type": "vocabulary"
}