{
  "id": "q_30",
  "vocab": [
    {
      "word": "rigorous curriculum",
      "ipa": "/ˈrɪɡərəs kəˈrɪkjələm/",
      "meaning": "chương trình học khắt khe và chính xác",
      "example": "The rigorous curriculum of my Law degree demands long hours of research and critical analysis.",
      "type": "vocabulary"
    },
    {
      "word": "be deeply engrossed in",
      "ipa": "/bi ˈdiːpli ɪnˈɡrəʊst ɪn/",
      "meaning": "say mê/hứng thú sâu sắc với cái gì",
      "example": "Lately, I’ve been deeply engrossed in my studies regarding sustainable urban development.",
      "type": "vocabulary"
    },
    {
      "word": "a niche field",
      "ipa": "/ə niːʃ fiːld/",
      "meaning": "một lĩnh vực chuyên biệt/thị trường ngách",
      "example": "I’m specializing in Ethnobotany, which is quite a niche field within the broader biological sciences.",
      "type": "vocabulary"
    },
    {
      "word": "hands-on experience",
      "ipa": "/hændz ɒn ɪkˈspɪəriəns/",
      "meaning": "kinh nghiệm thực hành thực tế",
      "example": "My course isn't just theory; we gain plenty of hands-on experience through weekly laboratory workshops.",
      "type": "vocabulary"
    },
    {
      "word": "intellectual curiosity",
      "ipa": "/ˌɪntəˈlektʃuəl ˌkjʊəriˈɒsəti/",
      "meaning": "sự ham học hỏi/tò mò về trí tuệ",
      "example": "I chose Philosophy primarily to satisfy my intellectual curiosity about the nature of existence.",
      "type": "vocabulary"
    },
    {
      "word": "major in",
      "ipa": "/ˈmeɪdʒər ɪn/",
      "meaning": "học chuyên ngành về",
      "example": "I decided to major in Finance to better understand the complexities of global markets.",
      "type": "vocabulary"
    },
    {
      "word": "subject matter",
      "ipa": "/ˈsʌbdʒɪkt ˈmætər/",
      "meaning": "nội dung chủ đề/vấn đề đang học",
      "example": "Although the subject matter is quite dense, the professors make it incredibly engaging.",
      "type": "vocabulary"
    },
    {
      "word": "pave the way for",
      "ipa": "/peɪv ðə weɪ fɔːr/",
      "meaning": "tạo tiền đề/mở đường cho (sự nghiệp)",
      "example": "I believe this qualification will pave the way for a successful career in international diplomacy.",
      "type": "vocabulary"
    },
    {
      "word": "core modules",
      "ipa": "/kɔːr ˈmɒdʒuːlz/",
      "meaning": "các học phần cốt lõi",
      "example": "My core modules this semester include advanced statistics and econometric modeling.",
      "type": "vocabulary"
    },
    {
      "word": "a cornerstone of",
      "ipa": "/ə ˈkɔːrnərstəʊn əv/",
      "meaning": "nền tảng/phần quan trọng nhất của",
      "example": "Ethics is a cornerstone of the journalism program I am currently enrolled in.",
      "type": "vocabulary"
    }
  ],
  "type": "vocabulary"
}