{
  "id": "q_31",
  "vocab": [
    {
      "word": "disposable income",
      "ipa": "/dɪˈspəʊzəbl ˈɪnkʌm/",
      "meaning": "thu nhập khả dụng (tiền dư sau khi trừ thuế và chi phí thiết yếu)",
      "example": "I only spend a small fraction of my disposable income on footwear, as I'm quite mindful of my savings.",
      "type": "vocabulary"
    },
    {
      "word": "bespoke",
      "ipa": "/bɪˈspəʊk/",
      "meaning": "hàng đặt may riêng, đóng riêng theo yêu cầu",
      "example": "I can’t quite afford bespoke shoes yet, but I dream of owning a pair tailored specifically to my feet.",
      "type": "vocabulary"
    },
    {
      "word": "retail therapy",
      "ipa": "/ˈriːteɪl ˈθerəpi/",
      "meaning": "mua sắm để xả stress, giải tỏa tâm trạng",
      "example": "On the rare occasion I engage in retail therapy, I might spend a bit more on a high-end pair of boots.",
      "type": "vocabulary"
    },
    {
      "word": "durability over aesthetics",
      "ipa": "/ˌdjʊərəˈbɪləti ˈəʊvə iːsˈθetɪks/",
      "meaning": "độ bền quan trọng hơn vẻ ngoài",
      "example": "I prioritize durability over aesthetics, so I'm willing to pay a premium for shoes that won't fall apart in six months.",
      "type": "vocabulary"
    },
    {
      "word": "bargain hunter",
      "ipa": "/ˈbɑːɡən ˈhʌntə(r)/",
      "meaning": "người săn hàng giá rẻ/giảm giá",
      "example": "As a dedicated bargain hunter, I rarely pay full price for shoes, preferring to wait for the end-of-season clearance.",
      "type": "vocabulary"
    },
    {
      "word": "a splurge",
      "ipa": "/ə splɜːdʒ/",
      "meaning": "một lần vung tay quá trán, mua đồ xa xỉ",
      "example": "Buying those designer heels was a bit of a splurge, but they were perfect for my brother's wedding.",
      "type": "vocabulary"
    },
    {
      "word": "mid-range brands",
      "ipa": "/mɪd reɪndʒ brændz/",
      "meaning": "các thương hiệu phân khúc tầm trung",
      "example": "I typically stick to mid-range brands that offer a decent balance between comfort and cost.",
      "type": "vocabulary"
    },
    {
      "word": "impulse buy",
      "ipa": "/ˈɪmpʌls baɪ/",
      "meaning": "việc mua sắm ngẫu hứng (không kế hoạch trước)",
      "example": "I try to avoid impulse buys when I'm at the mall, as I often end up with shoes I rarely wear.",
      "type": "vocabulary"
    },
    {
      "word": "investment piece",
      "ipa": "/ɪnˈvestmənt piːs/",
      "meaning": "món đồ đáng để đầu tư (đắt nhưng dùng lâu dài)",
      "example": "I view a solid pair of leather brogues as an investment piece that will stay in my wardrobe for a decade.",
      "type": "vocabulary"
    },
    {
      "word": "price point",
      "ipa": "/praɪs pɔɪnt/",
      "meaning": "mức giá (trên thị trường)",
      "example": "I’ve found that the $100 price point usually guarantees a level of comfort that cheaper alternatives lack.",
      "type": "vocabulary"
    }
  ],
  "type": "vocabulary"
}