{
  "id": "q_31",
  "vocab": [
    {
      "word": "breadth of knowledge",
      "ipa": "/bredθ əv ˈnɒlɪdʒ/",
      "meaning": "kiến thức rộng/tổng quát",
      "example": "I was drawn to Liberal Arts because it offers a significant breadth of knowledge across various disciplines.",
      "type": "vocabulary"
    },
    {
      "word": "vocational appeal",
      "ipa": "/vəʊˈkeɪʃənl əˈpiːl/",
      "meaning": "sức hút về mặt nghề nghiệp/thực hành",
      "example": "The vocational appeal of Nursing was the main driver behind my choice, as I wanted a hands-on career.",
      "type": "vocabulary"
    },
    {
      "word": "a stepping stone to",
      "ipa": "/ə ˈstepɪŋ stəʊn tuː/",
      "meaning": "bàn đạp/bước đệm để đạt được điều gì",
      "example": "I view a degree in Economics as a vital stepping stone to a future role in global policy-making.",
      "type": "vocabulary"
    },
    {
      "word": "intellectual curiosity",
      "ipa": "/ˌɪntəˈlektʃuəl ˌkjʊəriˈɒsəti/",
      "meaning": "sự tò mò về trí tuệ/ham học hỏi",
      "example": "My choice was fueled by a deep intellectual curiosity about how the human brain processes language.",
      "type": "vocabulary"
    },
    {
      "word": "lucrative career path",
      "ipa": "/ˈluːkrətɪv kəˈrɪər pɑːθ/",
      "meaning": "con đường sự nghiệp đem lại thu nhập cao",
      "example": "While I enjoy the subject, I cannot deny that Data Science is a particularly lucrative career path in today's economy.",
      "type": "vocabulary"
    },
    {
      "word": "unravel the mysteries of",
      "ipa": "/ʌnˈrævl ðə ˈmɪstriz əv/",
      "meaning": "khám phá/giải mã những bí ẩn của",
      "example": "I chose Astrophysics because I’ve always wanted to unravel the mysteries of the universe and black holes.",
      "type": "vocabulary"
    },
    {
      "word": "at the forefront of",
      "ipa": "/æt ðə ˈfɔːrfrʌnt əv/",
      "meaning": "ở vị trí tiên phong của",
      "example": "Studying Biotechnology allows me to be at the forefront of medical innovations and genetic research.",
      "type": "vocabulary"
    },
    {
      "word": "highly transferable skills",
      "ipa": "/ˈhaɪli trænsˈfɜːrəbl skɪlz/",
      "meaning": "kỹ năng có tính linh hoạt cao (áp dụng được nhiều nơi)",
      "example": "A History major provides highly transferable skills, such as critical analysis and persuasive writing.",
      "type": "vocabulary"
    },
    {
      "word": "personal fulfillment",
      "ipa": "/ˈpɜːrsənl fʊlˈfɪlmənt/",
      "meaning": "sự mãn nguyện/hài lòng cá nhân",
      "example": "I prioritized personal fulfillment over financial gain when I decided to pursue a degree in Fine Arts.",
      "type": "vocabulary"
    },
    {
      "word": "interdisciplinary nature",
      "ipa": "/ˌɪntəˈdɪsəplɪneri ˈneɪtʃər/",
      "meaning": "tính chất liên ngành (kết hợp nhiều ngành)",
      "example": "The interdisciplinary nature of Environmental Science, combining law and biology, was what ultimately swayed me.",
      "type": "vocabulary"
    }
  ],
  "type": "vocabulary"
}