{
  "id": "q_36",
  "vocab": [
    {
      "word": "firing on all cylinders",
      "ipa": "/ˈfaɪərɪŋ ɒn ɔːl ˈsɪlɪndərz/",
      "meaning": "hoạt động hết công suất, cực kỳ hiệu quả",
      "example": "I find that my brain is firing on all cylinders at 10 AM, making it the prime time for solving complex math problems.",
      "type": "idiom"
    },
    {
      "word": "reach one's peak",
      "ipa": "/riːtʃ wʌnz piːk/",
      "meaning": "chạm đến đỉnh cao (về năng suất/sự tập trung)",
      "example": "While others struggle to wake up, I usually reach my peak cognitive performance mid-morning.",
      "type": "idiom"
    },
    {
      "word": "hit a wall",
      "ipa": "/hɪt ə wɔːl/",
      "meaning": "đột ngột mệt mỏi, không thể tiếp tục (thường dùng cho buổi chiều)",
      "example": "I tend to hit a wall around 3 PM, so I prefer to get the bulk of my heavy reading done before lunch.",
      "type": "idiom"
    },
    {
      "word": "clear-headed",
      "ipa": "/ˌklɪə ˈhedɪd/",
      "meaning": "đầu óc tỉnh táo, minh mẫn",
      "example": "I’m much more clear-headed right after my morning coffee, which is why I never schedule study sessions for the late afternoon.",
      "type": "idiom"
    },
    {
      "word": "in the zone",
      "ipa": "/ɪn ðə zoʊn/",
      "meaning": "trạng thái cực kỳ tập trung, làm việc trôi chảy",
      "example": "Once I sit down at my desk at 8 AM, I’m quickly in the zone and can ignore all distractions.",
      "type": "idiom"
    },
    {
      "word": "take the bull by the horns",
      "ipa": "/teɪk ðə bʊl baɪ ðə hɔːrnz/",
      "meaning": "trực tiếp đối mặt với khó khăn (học những môn khó nhất ngay từ sáng sớm)",
      "example": "I like to take the bull by the horns in the morning by tackling the most challenging subjects first.",
      "type": "idiom"
    },
    {
      "word": "get into the swing of things",
      "ipa": "/ɡet ˈɪntu ðə swɪŋ əv θɪŋz/",
      "meaning": "bắt nhịp với công việc/guồng quay",
      "example": "It takes me a few hours to get into the swing of things, so the afternoon is actually better for my creative writing.",
      "type": "idiom"
    },
    {
      "word": "recharge one's batteries",
      "ipa": "/ˌriːˈtʃɑːrdʒ wʌnz ˈbætəriz/",
      "meaning": "nạp lại năng lượng",
      "example": "I use the morning to exercise and recharge my batteries so that I can stay focused during afternoon lectures.",
      "type": "idiom"
    },
    {
      "word": "off the pace",
      "ipa": "/ɔːf ðə peɪs/",
      "meaning": "chậm chạp hơn, không theo kịp tốc độ (khi mệt mỏi)",
      "example": "By late afternoon, I feel a bit off the pace, and my ability to memorize vocabulary significantly drops.",
      "type": "idiom"
    },
    {
      "word": "at one's wits' end",
      "ipa": "/æt wʌnz wɪts end/",
      "meaning": "kiệt sức, không còn tâm trí để giải quyết việc gì",
      "example": "If I leave my revision until the evening, I’m often at my wits' end and end up absorbing nothing.",
      "type": "idiom"
    }
  ],
  "type": "idiom"
}