{
  "id": "q_3",
  "vocab": [
    {
      "word": "a whale of a time",
      "ipa": "/ə weɪl əv ə taɪm/",
      "meaning": "có một khoảng thời gian cực kỳ vui vẻ",
      "example": "I used to have a whale of a time playing hide-and-seek with the neighborhood kids every summer evening.",
      "type": "idiom"
    },
    {
      "word": "lose oneself in something",
      "ipa": "/luːz wʌnˈself ɪn ˈsʌmθɪŋ/",
      "meaning": "mải mê, chìm đắm hoàn toàn vào việc gì đó",
      "example": "I could easily lose myself in a drawing for hours, completely oblivious to everything happening around me.",
      "type": "idiom"
    },
    {
      "word": "be into something",
      "ipa": "/bi ˈɪntə ˈsʌmθɪŋ/",
      "meaning": "cực kỳ say mê hoặc thích thú điều gì",
      "example": "Back in primary school, I was really into collecting rare stamps from different corners of the world.",
      "type": "idiom"
    },
    {
      "word": "have a go at something",
      "ipa": "/hæv ə ɡəʊ æt ˈsʌmθɪŋ/",
      "meaning": "thử làm một việc gì đó (thường là lần đầu)",
      "example": "My parents encouraged me to have a go at various sports, from swimming to martial arts.",
      "type": "idiom"
    },
    {
      "word": "at a tender age",
      "ipa": "/æt ə ˈtendə(r) eɪdʒ/",
      "meaning": "khi còn ở độ tuổi rất nhỏ (tuổi thơ ngây)",
      "example": "I developed a passion for playing the piano at the tender age of six.",
      "type": "idiom"
    },
    {
      "word": "take a fancy to",
      "ipa": "/teɪk ə ˈfænsi tuː/",
      "meaning": "bắt đầu trở nên thích thú với cái gì",
      "example": "I suddenly took a fancy to building model airplanes after watching a documentary about aviation.",
      "type": "idiom"
    },
    {
      "word": "the apple of one's eye",
      "ipa": "/ði ˈæpl əv wʌnz aɪ/",
      "meaning": "vật quý báu hoặc người được yêu chiều (có thể dùng để nói về sở thích quý giá)",
      "example": "My collection of hand-painted toy soldiers was the apple of my eye when I was ten.",
      "type": "idiom"
    },
    {
      "word": "be a breeze",
      "ipa": "/bi ə briːz/",
      "meaning": "rất dễ dàng (thường nói về một kỹ năng học được từ nhỏ)",
      "example": "Learning to ride a bike was a breeze for me because I spent every afternoon practicing in the garden.",
      "type": "idiom"
    },
    {
      "word": "from the word go",
      "ipa": "/frəm ðə wɜːd ɡəʊ/",
      "meaning": "ngay từ lúc bắt đầu",
      "example": "I was fascinated by storytelling from the word go, often making up elaborate plots for my action figures.",
      "type": "idiom"
    },
    {
      "word": "pass the time",
      "ipa": "/pɑːs ðə taɪm/",
      "meaning": "giết thời gian, làm gì đó cho đỡ buồn chán",
      "example": "Solving jigsaw puzzles was my favorite way to pass the time on rainy days when I couldn't go outside.",
      "type": "idiom"
    }
  ],
  "type": "idiom"
}