{
  "id": "q_42",
  "vocab": [
    {
      "word": "solitary retreat",
      "ipa": "/ˈsɒlɪtri rɪˈtriːt/",
      "meaning": "nơi ẩn dật/lui tới một mình để tĩnh tâm",
      "example": "On weekends, I often seek out a solitary retreat in the mountains to escape the digital tether of modern life.",
      "type": "vocabulary"
    },
    {
      "word": "auditory onslaught",
      "ipa": "/ˈɔːdɪtəri ˈɒnslɔːt/",
      "meaning": "sự tấn công dồn dập về thính giác (tiếng ồn quá mức)",
      "example": "I find the auditory onslaught of a crowded nightclub rather draining, so I tend to avoid them on my days off.",
      "type": "vocabulary"
    },
    {
      "word": "pastoral setting",
      "ipa": "/ˈpɑːstərəl ˈsetɪŋ/",
      "meaning": "khung cảnh đồng quê yên bình",
      "example": "There is something incredibly therapeutic about spending a Saturday in a pastoral setting, far from city sirens.",
      "type": "vocabulary"
    },
    {
      "word": "rejuvenate one’s senses",
      "ipa": "/rɪˈdʒuːvəneɪt wʌnz sensɪz/",
      "meaning": "làm mới/vực lại các giác quan",
      "example": "Quiet environments help rejuvenate my senses and prepare me for the rigors of the upcoming work week.",
      "type": "vocabulary"
    },
    {
      "word": "vibrant social hub",
      "ipa": "/ˈvaɪbrənt ˈsəʊʃl hʌb/",
      "meaning": "trung tâm xã hội náo nhiệt",
      "example": "Occasionally, I enjoy visiting a vibrant social hub like a street food market to soak up the local energy.",
      "type": "vocabulary"
    },
    {
      "word": "ambient noise",
      "ipa": "/ˈæmbiənt nɔɪz/",
      "meaning": "tiếng ồn xung quanh/tiếng nhiễu nền",
      "example": "I don't mind a bit of ambient noise in a coffee shop, but a full-blown construction site is where I draw the line.",
      "type": "vocabulary"
    },
    {
      "word": "secluded",
      "ipa": "/sɪˈkluːdɪd/",
      "meaning": "hẻo lánh/tách biệt với bên ngoài",
      "example": "We managed to find a secluded spot by the river that remained peaceful despite it being a public holiday.",
      "type": "vocabulary"
    },
    {
      "word": "mellow out",
      "ipa": "/ˈmeləʊ aʊt/",
      "meaning": "thư giãn/trở nên điềm tĩnh hơn",
      "example": "I like to mellow out in a quiet botanical garden where the only sound is the wind rustling through the leaves.",
      "type": "vocabulary"
    },
    {
      "word": "urban grit",
      "ipa": "/ˈɜːrbən ɡrɪt/",
      "meaning": "sự xô bồ/góc cạnh của đời sống đô thị",
      "example": "While some love the urban grit and loud music of the city, I prefer the hushed tones of a suburban park.",
      "type": "vocabulary"
    },
    {
      "word": "state of equilibrium",
      "ipa": "/steɪt əv ˌiːkwɪˈlɪbriəm/",
      "meaning": "trạng thái cân bằng (về tâm trí)",
      "example": "Finding a quiet space is essential for me to reach a state of equilibrium after a chaotic week of deadlines.",
      "type": "vocabulary"
    }
  ],
  "type": "vocabulary"
}