{
  "id": "q_46",
  "vocab": [
    {
      "word": "strike up a conversation",
      "ipa": "/straɪk ʌp ə ˌkɒnvəˈseɪʃn/",
      "meaning": "chủ động bắt chuyện",
      "example": "I occasionally strike up a conversation with fellow commuters to pass the time during long train journeys.",
      "type": "collocation"
    },
    {
      "word": "social butterfly",
      "ipa": "/ˈsəʊʃl ˈbʌtəflaɪ/",
      "meaning": "người hướng ngoại, khéo giao tiếp",
      "example": "My best friend is a bit of a social butterfly, always chatting with strangers at the park as if they were old friends.",
      "type": "collocation"
    },
    {
      "word": "fleeting encounter",
      "ipa": "/ˈfliːtɪŋ ɪnˈkaʊntə(r)/",
      "meaning": "cuộc gặp gỡ thoáng qua",
      "example": "It was just a fleeting encounter in a crowded café, but the woman's advice on traveling really stuck with me.",
      "type": "collocation"
    },
    {
      "word": "bridge the gap",
      "ipa": "/brɪdʒ ðə ɡæp/",
      "meaning": "xóa bỏ khoảng cách (về thế hệ, văn hóa, sự xa lạ)",
      "example": "A simple comment about the weather can often bridge the gap between two people waiting at a bus stop.",
      "type": "collocation"
    },
    {
      "word": "break the ice",
      "ipa": "/breɪk ðə aɪs/",
      "meaning": "phá vỡ bầu không khí ngượng ngùng",
      "example": "I usually try to break the ice with a light-hearted joke when I'm sat next to someone I don't know at a gala.",
      "type": "collocation"
    },
    {
      "word": "random act of kindness",
      "ipa": "/ˈrændəm ækt əv ˈkaɪndnəs/",
      "meaning": "một cử chỉ tử tế ngẫu nhiên",
      "example": "Talking to a lonely elderly person in the supermarket is a small, random act of kindness that can brighten their day.",
      "type": "collocation"
    },
    {
      "word": "social etiquette",
      "ipa": "/ˈsəʊʃl ˈetɪket/",
      "meaning": "phép tắc xã giao",
      "example": "Depending on the local social etiquette, initiating a chat with a stranger might be seen as either friendly or intrusive.",
      "type": "collocation"
    },
    {
      "word": "shared predicament",
      "ipa": "/ʃeəd prɪˈdɪkəmənt/",
      "meaning": "tình huống khó khăn chung",
      "example": "We started talking because of our shared predicament when the elevator got stuck between floors for twenty minutes.",
      "type": "collocation"
    },
    {
      "word": "exchange pleasantries",
      "ipa": "/ɪksˈtʃeɪndʒ ˈplezntriz/",
      "meaning": "trao đổi những lời xã giao lịch sự",
      "example": "I don't usually share personal details, but I’m happy to exchange pleasantries with people while waiting in a queue.",
      "type": "collocation"
    },
    {
      "word": "sense of camaraderie",
      "ipa": "/sens əv ˌkæməˈrɑːdəri/",
      "meaning": "cảm giác thân thiết, đồng lòng (giữa những người cùng cảnh ngộ)",
      "example": "There was a sudden sense of camaraderie among the stranded passengers, leading to several deep conversations.",
      "type": "collocation"
    }
  ],
  "type": "collocation"
}