{
  "id": "q_47",
  "vocab": [
    {
      "word": "a lone wolf",
      "ipa": "/ə ləʊn wʊlf/",
      "meaning": "một người thích làm việc/hoạt động độc lập",
      "example": "When it comes to tackling complex math problems, I’m a bit of a lone wolf because I need total concentration.",
      "type": "idiom"
    },
    {
      "word": "put our heads together",
      "ipa": "/pʊt ˈaʊər hedz təˈɡeðər/",
      "meaning": "cùng nhau suy nghĩ/hội ý để giải quyết vấn đề",
      "example": "If we hit a brick wall with the project, it's often better to put our heads together and brainstorm a solution.",
      "type": "idiom"
    },
    {
      "word": "pick someone's brains",
      "ipa": "/pɪk ˈsʌmwʌnz breɪnz/",
      "meaning": "hỏi ý kiến ai đó am hiểu để học hỏi",
      "example": "I love group sessions because they provide a golden opportunity to pick my classmates' brains on tricky topics.",
      "type": "idiom"
    },
    {
      "word": "two heads are better than one",
      "ipa": "/tuː hedz ɑːr ˈbetər ðæn wʌn/",
      "meaning": "một cây làm chẳng nên non, ba cây chụm lại nên hòn núi cao",
      "example": "I’m a firm believer that two heads are better than one, especially when analyzing intricate literary texts.",
      "type": "idiom"
    },
    {
      "word": "in the doldrums",
      "ipa": "/ɪn ðə ˈdəʊldrəmz/",
      "meaning": "trạng thái buồn chán, thiếu động lực",
      "example": "Studying alone for too long can leave me in the doldrums, so I occasionally join a group to lift my spirits.",
      "type": "idiom"
    },
    {
      "word": "keep your nose to the grindstone",
      "ipa": "/kiːp jɔːr nəʊz tə ðə ˈɡraɪndstəʊn/",
      "meaning": "làm việc/học tập liên tục và chăm chỉ",
      "example": "If I study by myself, I find it much easier to keep my nose to the grindstone without being distracted by small talk.",
      "type": "idiom"
    },
    {
      "word": "on the same page",
      "ipa": "/ɒn ðə seɪm peɪdʒ/",
      "meaning": "thống nhất/cùng chung quan điểm",
      "example": "The main struggle of studying with others is ensuring that everyone is on the same page regarding the goals of the session.",
      "type": "idiom"
    },
    {
      "word": "sink or swim",
      "ipa": "/sɪŋk ɔːr swɪm/",
      "meaning": "tự lực cánh sinh (tự mình thành công hoặc thất bại)",
      "example": "Studying alone feels like a sink or swim situation, which actually pushes me to take full responsibility for my progress.",
      "type": "idiom"
    },
    {
      "word": "burn the midnight oil",
      "ipa": "/bɜːrn ðə ˈmɪdnaɪt ɔɪl/",
      "meaning": "thức khuya để học bài hay làm việc",
      "example": "During finals week, my friends and I often burn the midnight oil together at a 24-hour cafe.",
      "type": "idiom"
    },
    {
      "word": "all hands on deck",
      "ipa": "/ɔːl hændz ɒn dek/",
      "meaning": "tất cả mọi người cùng chung tay giúp sức",
      "example": "When a deadline is looming, it's definitely an all hands on deck approach to finish the group assignment on time.",
      "type": "idiom"
    }
  ],
  "type": "idiom"
}